six_totp/__init__.py
six_totp/core.py
six_totp/tests/test_core.py
six_totp-1.0.0.dist-info/licenses/LICENSE
six_totp-1.0.0.dist-info/METADATA
six_totp-1.0.0.dist-info/WHEEL
six_totp-1.0.0.dist-info/top_level.txt
six_totp-1.0.0.dist-info/RECORD
