Metadata-Version: 2.4
Name: six_totp
Version: 1.0.0
Summary: six_totp is a lightweight Python library for generating 6-digit passcodes.
Author-email: Iliyan Georgiev <georgiev.iliyan09@gmail.com>
License: MIT License
Project-URL: Homepage, https://github.com/GeorgievIliyan/six_totp
Requires-Python: >=3.8
License-File: LICENSE
Dynamic: license-file
